napari_labelimg4classification/__init__.py
napari_labelimg4classification/_dock_widget.py
napari_labelimg4classification/_tests/__init__.py
napari_labelimg4classification/_tests/test_dock_widget.py
napari_labelimg4classification-0.1.1.dist-info/LICENSE
napari_labelimg4classification-0.1.1.dist-info/METADATA
napari_labelimg4classification-0.1.1.dist-info/WHEEL
napari_labelimg4classification-0.1.1.dist-info/entry_points.txt
napari_labelimg4classification-0.1.1.dist-info/top_level.txt
napari_labelimg4classification-0.1.1.dist-info/RECORD
