Metadata-Version: 2.1
Name: napari-labelimg4classification
Version: 0.1.1
Summary: Image-Level labeling tool
Home-page: https://github.com/hiroalchem/napari-labelimg4classification
Author: Hiroki Kawai
Author-email: h.kawai888@gmail.com
License: MIT
Project-URL: Bug Tracker, https://github.com/hiroalchem/napari-labelimg4classification/issues
Project-URL: Documentation, https://github.com/hiroalchem/napari-labelimg4classification#README.md
Project-URL: Source Code, https://github.com/hiroalchem/napari-labelimg4classification
Project-URL: User Support, https://github.com/hiroalchem/napari-labelimg4classification/issues
Platform: UNKNOWN
Classifier: Development Status :: 2 - Pre-Alpha
Classifier: Intended Audience :: Developers
Classifier: Framework :: napari
Classifier: Topic :: Software Development :: Testing
Classifier: Programming Language :: Python
Classifier: Programming Language :: Python :: 3
Classifier: Programming Language :: Python :: 3.7
Classifier: Programming Language :: Python :: 3.8
Classifier: Programming Language :: Python :: 3.9
Classifier: Operating System :: OS Independent
Classifier: License :: OSI Approved :: MIT License
Requires-Python: >=3.7
License-File: LICENSE
Requires-Dist: napari-plugin-engine (>=0.1.4)
Requires-Dist: napari
Requires-Dist: numpy
Requires-Dist: napari-tools-menu
Requires-Dist: pandas
